LICENSE
kubectlfr/__init__.py
kubectlfr/main.py
kubectlfr/translation.py
kubectlfr-1.0.2.dist-info/entry_points.txt
kubectlfr-1.0.2.dist-info/LICENSE
kubectlfr-1.0.2.dist-info/WHEEL
kubectlfr-1.0.2.dist-info/METADATA
kubectlfr-1.0.2.dist-info/RECORD
