Metadata-Version: 2.1
Name: kubectlfr
Version: 1.0.2
Summary: Utilitaire de contrôle de Kubernetes
Home-page: https://github.com/theophanevie/kubectlfr
License: MIT
Keywords: kubernetes,kubectl,francais
Author: Théophane Vié
Author-email: theophane.vie@petit-nuage.org
Requires-Python: >=3.9,<4.0
Classifier: License :: OSI Approved :: MIT License
Classifier: Programming Language :: Python :: 3
Classifier: Programming Language :: Python :: 3.9
Requires-Dist: click (>=8.0.3,<9.0.0)
Project-URL: Repository, https://github.com/theophanevie/kubectlfr
